Metadata-Version: 1.1
Name: fixlsx
Version: 0.0.1
Summary: A very basic calculator
Home-page: UNKNOWN
Author: Ereteam
Author-email: devadm@ereteam.com
License: UNKNOWN
Keywords: calculator
Platform: UNKNOWN
Classifier: Development Status :: 5 - Production/Stable
Classifier: Intended Audience :: Education
Classifier: Operating System :: Microsoft :: Windows :: Windows 10
Classifier: Programming Language :: Python :: 3
